EXP_6_2019A3PS0361H/four_bit_adder.v
module fourbitadder (a,b,s,c);
input [3:0] a;
input [3:0] b;
output [3:0] s;
output c;
assign {c,s} = a + b;
endmodule

EXP_6_2019A3PS0361H/bcd_adder.v
`include "four_bit_adder.v"

module bcdadder (a,b,s,c);
input [3:0] a;
input [3:0] b;
output [3:0] s;
output c;

wire [3:0] w1;
wire w3;

wire w2;
assign w2 = (w1[3] & w1[2]) | (w1[3] & w1[1]);

assign w4  = w3 | w2;

wire [3:0] w5;
assign w5 = {1'b0,w4, w4, 1'b0};

fourbitadder adder1(a,b,w1,w3);
fourbitadder adder2(w1,w5,s,c);

endmodule

EXP_6_2019A3PS0361H/bcd_adder_tb.v
`timescale 1ns / 1ns
`include "bcd_adder.v"
module bcdaddertb;

reg [3:0] a;
reg [3:0] b;
wire [3:0] s;
wire c;

bcdadder dut (.a(a), .b(b), .s(s), .c(c));

initial begin
$dumpfile("bcd_adder_graph.vcd");
$dumpvars(0,bcdaddertb);

a = 4'b0000;
b = 4'b0000;
#10;

a = 4'b0001;
b = 4'b0001;
#10;

a = 4'b0010;
b = 4'b0010;
#10;

a = 4'b0011;
b = 4'b0011;
#10;

a = 4'b0100;
b = 4'b0100;
#10;

a = 4'b0101;
b = 4'b0101;
#10;

a = 4'b0110;
b = 4'b0110;
#10;

a = 4'b0111;
b = 4'b0111;
#10;


a = 4'b1000;
b = 4'b1000;
#10;

a = 4'b1001;
b = 4'b1001;
#10;

a = 4'b1010;

b = 4'b1010;
#10;

a = 4'b1011;
b = 4'b1011;
#10;

a = 4'b1100;
b = 4'b1100;
#10;

a = 4'b1101;
b = 4'b1101;
#10;

a = 4'b1110;
b = 4'b1110;
#10;

a = 4'b1111;
b = 4'b1111;
#10;

end

endmodule

EXP_6_2019A3PS0361H/bcd_adder_graph.vcd
$date
	Thu Oct  8 10:41:42 2020
$end
$version
	Icarus Verilog
$end
$timescale
	1ns
$end
$scope module bcdaddertb $end
$var wire 4 ! s [3:0] $end
$var wire 1 " c $end
$var reg 4 # a [3:0] $end
$var reg 4 $ b [3:0] $end
$scope module dut $end
$var wire 4 % a [3:0] $end
$var wire 4 & b [3:0] $end
$var wire 1 ' w2 $end
$var wire 1 ( w4 $end
$var wire 4 ) w5 [3:0] $end
$var wire 1 * w3 $end
$var wire 4 + w1 [3:0] $end
$var wire 4 , s [3:0] $end
$var wire 1 " c $end
$scope module adder1 $end
$var wire 4 - a [3:0] $end
$var wire 4 . b [3:0] $end
$var wire 4 / s [3:0] $end
$var wire 1 * c $end
$upscope $end
$scope module adder2 $end
$var wire 4 0 a [3:0] $end
$var wire 4 1 b [3:0] $end
$var wire 4 2 s [3:0] $end
$var wire 1 " c $end
$upscope $end
$upscope $end
$upscope $end
$enddefinitions $end
#0
$dumpvars
b0 2
b0 1
b0 0
b0 /
b0 .
b0 -
b0 ,
b0 +
0*
b0 )
0(
0'
b0 &
b0 %
b0 $
b0 #
0"
b0 !
$end
#10
b10 !
b10 ,
b10 2
b10 +
b10 /
b10 0
b1 $
b1 &
b1 .
b1 #
b1 %
b1 -
#20
b100 !
b100 ,
b100 2
b100 +
b100 /
b100 0
b10 $
b10 &
b10 .
b10 #
b10 %
b10 -
#30
b110 !
b110 ,
b110 2
b110 +
b110 /
b110 0
b11 $
b11 &
b11 .
b11 #
b11 %
b11 -
#40
b1000 !
b1000 ,
b1000 2
b1000 +
b1000 /
b1000 0
b100 $
b100 &
b100 .
b100 #
b100 %
b100 -
#50
1"
b110 )
b110 1
1(
1'
b0 !
b0 ,
b0 2
b1010 +
b1010 /
b1010 0
b101 $
b101 &
b101 .
b101 #
b101 %
b101 -
#60
b10 !
b10 ,
b10 2
b1100 +
b1100 /
b1100 0
b110 $
b110 &
b110 .
b110 #
b110 %
b110 -
#70
b100 !
b100 ,
b100 2
b1110 +
b1110 /
b1110 0
b111 $
b111 &
b111 .
b111 #
b111 %
b111 -
#80
0'
b110 !
b110 ,
b110 2
0"
1*
b0 +
b0 /
b0 0
b1000 $
b1000 &
b1000 .
b1000 #
b1000 %
b1000 -
#90
b1000 !
b1000 ,
b1000 2
b10 +
b10 /
b10 0
b1001 $
b1001 &
b1001 .
b1001 #
b1001 %
b1001 -
#100
b1010 !
b1010 ,
b1010 2
b100 +
b100 /
b100 0
b1010 $
b1010 &
b1010 .
b1010 #
b1010 %
b1010 -
#110
b1100 !
b1100 ,
b1100 2
b110 +
b110 /
b110 0
b1011 $
b1011 &
b1011 .
b1011 #
b1011 %
b1011 -
#120
b1110 !
b1110 ,
b1110 2
b1000 +
b1000 /
b1000 0
b1100 $
b1100 &
b1100 .
b1100 #
b1100 %
b1100 -
#130
1'
b0 !
b0 ,
b0 2
1"
b1010 +
b1010 /
b1010 0
b1101 $
b1101 &
b1101 .
b1101 #
b1101 %
b1101 -
#140
b10 !
b10 ,
b10 2
b1100 +
b1100 /
b1100 0
b1110 $
b1110 &
b1110 .
b1110 #
b1110 %
b1110 -
#150
b100 !
b100 ,
b100 2
b1110 +
b1110 /
b1110 0
b1111 $
b1111 &
b1111 .
b1111 #
b1111 %
b1111 -
